[
  {
    "id": 1865354,
    "startTime": 1750947992000,
    "lastUpdatedTime": 1750956963000,
    "etrTime": 1750982081000,
    "title": "Outage",
    "numPeople": 44,
    "status": "Dispatched",
    "cause": "Investigating",
    "identifier": "198592",
    "latitude": 47.67789,
    "longitude": -122.32751,
    "polygons": {
      "type": "polygon",
      "spatialReference": {
        "latestWkid": 4326,
        "wkid": 4326
      },
      "rings": [
        [
          [
            -122.32785,
            47.6774
          ],
          [
            -122.3281,
            47.67741
          ],
          [
            -122.32822,
            47.67745
          ],
          [
            -122.32831,
            47.67753
          ],
          [
            -122.32837,
            47.67764
          ],
          [
            -122.32838,
            47.67776
          ],
          [
            -122.32834,
            47.67788
          ],
          [
            -122.32818,
            47.67801
          ],
          [
            -122.32807,
            47.67803
          ],
          [
            -122.32809,
            47.6781
          ],
          [
            -122.32806,
            47.67822
          ],
          [
            -122.328,
            47.67833
          ],
          [
            -122.32786,
            47.67842
          ],
          [
            -122.32774,
            47.67844
          ],
          [
            -122.32762,
            47.67842
          ],
          [
            -122.32748,
            47.67833
          ],
          [
            -122.32745,
            47.67829
          ],
          [
            -122.32745,
            47.6783
          ],
          [
            -122.32732,
            47.6784
          ],
          [
            -122.32716,
            47.67842
          ],
          [
            -122.32699,
            47.67834
          ],
          [
            -122.32681,
            47.67817
          ],
          [
            -122.32674,
            47.67799
          ],
          [
            -122.32673,
            47.67787
          ],
          [
            -122.32677,
            47.67775
          ],
          [
            -122.32685,
            47.67766
          ],
          [
            -122.32696,
            47.67761
          ],
          [
            -122.32709,
            47.6776
          ],
          [
            -122.32722,
            47.67765
          ],
          [
            -122.32733,
            47.67774
          ],
          [
            -122.32732,
            47.67769
          ],
          [
            -122.32741,
            47.67753
          ],
          [
            -122.32757,
            47.67744
          ]
        ]
      ],
      "hasZ": false,
      "hasM": false
    },
    "city": "North Seattle",
    "state": "WA"
  },
  {
    "id": 1865376,
    "startTime": 1750950518000,
    "lastUpdatedTime": 1750956963000,
    "etrTime": 1750982081000,
    "title": "Outage",
    "numPeople": 12,
    "status": "Dispatched",
    "cause": "Investigating",
    "identifier": "198594",
    "latitude": 47.63078,
    "longitude": -122.27808,
    "polygons": {
      "type": "polygon",
      "spatialReference": {
        "latestWkid": 4326,
        "wkid": 4326
      },
      "rings": [
        [
          [
            -122.2774,
            47.6303
          ],
          [
            -122.27809,
            47.63016
          ],
          [
            -122.27823,
            47.63017
          ],
          [
            -122.27907,
            47.63054
          ],
          [
            -122.27918,
            47.63069
          ],
          [
            -122.27918,
            47.63089
          ],
          [
            -122.2791,
            47.63101
          ],
          [
            -122.27898,
            47.63109
          ],
          [
            -122.27783,
            47.63143
          ],
          [
            -122.27764,
            47.63142
          ],
          [
            -122.27752,
            47.63135
          ],
          [
            -122.27719,
            47.63098
          ],
          [
            -122.27711,
            47.63083
          ],
          [
            -122.27711,
            47.63071
          ],
          [
            -122.27719,
            47.63045
          ],
          [
            -122.27728,
            47.63036
          ]
        ]
      ],
      "hasZ": false,
      "hasM": false
    },
    "city": "North Seattle",
    "state": "WA"
  },
  {
    "id": 1865315,
    "startTime": 1750945207000,
    "lastUpdatedTime": 1750956963000,
    "etrTime": 1750967681000,
    "title": "Outage",
    "numPeople": 8,
    "status": "Dispatched",
    "cause": "Investigating",
    "identifier": "198590",
    "latitude": 47.48149,
    "longitude": -122.33804,
    "polygons": {
      "type": "polygon",
      "spatialReference": {
        "latestWkid": 4326,
        "wkid": 4326
      },
      "rings": [
        [
          [
            -122.33802,
            47.48229
          ],
          [
            -122.33744,
            47.48161
          ],
          [
            -122.33739,
            47.4815
          ],
          [
            -122.33742,
            47.48096
          ],
          [
            -122.3375,
            47.48084
          ],
          [
            -122.33764,
            47.48076
          ],
          [
            -122.33831,
            47.48076
          ],
          [
            -122.33845,
            47.48084
          ],
          [
            -122.33853,
            47.48098
          ],
          [
            -122.33858,
            47.48192
          ],
          [
            -122.33855,
            47.4822
          ],
          [
            -122.33845,
            47.48233
          ],
          [
            -122.3383,
            47.48239
          ],
          [
            -122.33814,
            47.48237
          ]
        ]
      ],
      "hasZ": false,
      "hasM": false
    },
    "city": "South Seattle",
    "state": "WA"
  },
  {
    "id": 1865346,
    "startTime": 1750947249000,
    "lastUpdatedTime": 1750956963000,
    "etrTime": 1750978481000,
    "title": "Outage",
    "numPeople": 2,
    "status": "Dispatched",
    "cause": "Investigating",
    "identifier": "198591",
    "latitude": 47.50557,
    "longitude": -122.26864,
    "polygons": {
      "type": "polygon",
      "spatialReference": {
        "latestWkid": 4326,
        "wkid": 4326
      },
      "rings": [
        [
          [
            -122.26853,
            47.50535
          ],
          [
            -122.26864,
            47.50529
          ],
          [
            -122.26876,
            47.50527
          ],
          [
            -122.26888,
            47.5053
          ],
          [
            -122.269,
            47.50539
          ],
          [
            -122.26906,
            47.50549
          ],
          [
            -122.26909,
            47.50561
          ],
          [
            -122.26906,
            47.50573
          ],
          [
            -122.269,
            47.50583
          ],
          [
            -122.26886,
            47.50592
          ],
          [
            -122.26874,
            47.50595
          ],
          [
            -122.26862,
            47.50592
          ],
          [
            -122.26848,
            47.50583
          ],
          [
            -122.26841,
            47.50573
          ],
          [
            -122.26839,
            47.50559
          ],
          [
            -122.26843,
            47.50545
          ]
        ]
      ],
      "hasZ": false,
      "hasM": false
    },
    "city": "South Seattle",
    "state": "WA"
  },
  {
    "id": 1865390,
    "startTime": 1750951560000,
    "lastUpdatedTime": 1750956963000,
    "etrTime": 1750978481000,
    "title": "Outage",
    "numPeople": 1,
    "cause": "Investigating",
    "identifier": "198596",
    "latitude": 47.62835,
    "longitude": -122.2794,
    "polygons": {
      "type": "polygon",
      "spatialReference": {
        "latestWkid": 4326,
        "wkid": 4326
      },
      "rings": [
        [
          [
            -122.27918,
            47.62809
          ],
          [
            -122.27929,
            47.62803
          ],
          [
            -122.27941,
            47.62802
          ],
          [
            -122.27953,
            47.62805
          ],
          [
            -122.27965,
            47.62813
          ],
          [
            -122.27972,
            47.62823
          ],
          [
            -122.27974,
            47.62835
          ],
          [
            -122.27972,
            47.62847
          ],
          [
            -122.27965,
            47.62858
          ],
          [
            -122.27951,
            47.62867
          ],
          [
            -122.27939,
            47.62869
          ],
          [
            -122.27927,
            47.62867
          ],
          [
            -122.27914,
            47.62858
          ],
          [
            -122.27907,
            47.62847
          ],
          [
            -122.27904,
            47.62833
          ],
          [
            -122.27909,
            47.6282
          ]
        ]
      ],
      "hasZ": false,
      "hasM": false
    },
    "city": "North Seattle",
    "state": "WA"
  },
  {
    "id": 1865450,
    "startTime": 1750955614000,
    "lastUpdatedTime": 1750956963000,
    "etrTime": 1750978481000,
    "title": "Outage",
    "numPeople": 1,
    "cause": "Investigating",
    "identifier": "198599",
    "latitude": 47.63495,
    "longitude": -122.29925,
    "polygons": {
      "type": "polygon",
      "spatialReference": {
        "latestWkid": 4326,
        "wkid": 4326
      },
      "rings": [
        [
          [
            -122.29903,
            47.63469
          ],
          [
            -122.29914,
            47.63463
          ],
          [
            -122.29926,
            47.63461
          ],
          [
            -122.29938,
            47.63465
          ],
          [
            -122.2995,
            47.63473
          ],
          [
            -122.29957,
            47.63483
          ],
          [
            -122.29959,
            47.63495
          ],
          [
            -122.29957,
            47.63507
          ],
          [
            -122.2995,
            47.63517
          ],
          [
            -122.29936,
            47.63527
          ],
          [
            -122.29924,
            47.63529
          ],
          [
            -122.29912,
            47.63527
          ],
          [
            -122.29899,
            47.63517
          ],
          [
            -122.29892,
            47.63507
          ],
          [
            -122.29889,
            47.63493
          ],
          [
            -122.29894,
            47.6348
          ]
        ]
      ],
      "hasZ": false,
      "hasM": false
    },
    "city": "North Seattle",
    "state": "WA"
  },
  {
    "id": 1865458,
    "startTime": 1750956342000,
    "lastUpdatedTime": 1750956963000,
    "etrTime": 1750978481000,
    "title": "Outage",
    "numPeople": 1,
    "cause": "Investigating",
    "identifier": "198601",
    "latitude": 47.49009,
    "longitude": -122.25124,
    "polygons": {
      "type": "polygon",
      "spatialReference": {
        "latestWkid": 4326,
        "wkid": 4326
      },
      "rings": [
        [
          [
            -122.25087,
            47.48976
          ],
          [
            -122.25098,
            47.4897
          ],
          [
            -122.2511,
            47.48969
          ],
          [
            -122.25122,
            47.48972
          ],
          [
            -122.25134,
            47.4898
          ],
          [
            -122.25141,
            47.4899
          ],
          [
            -122.25143,
            47.49002
          ],
          [
            -122.25141,
            47.49015
          ],
          [
            -122.25134,
            47.49025
          ],
          [
            -122.2512,
            47.49034
          ],
          [
            -122.25108,
            47.49036
          ],
          [
            -122.25096,
            47.49034
          ],
          [
            -122.25082,
            47.49025
          ],
          [
            -122.25075,
            47.49015
          ],
          [
            -122.25073,
            47.49
          ],
          [
            -122.25077,
            47.48987
          ]
        ]
      ],
      "hasZ": false,
      "hasM": false
    },
    "city": "South Seattle",
    "state": "WA"
  },
  {
    "id": 1865459,
    "startTime": 1750956402000,
    "lastUpdatedTime": 1750956963000,
    "etrTime": 1750978481000,
    "title": "Outage",
    "numPeople": 1,
    "cause": "Investigating",
    "identifier": "198602",
    "latitude": 47.68347,
    "longitude": -122.36308,
    "polygons": {
      "type": "polygon",
      "spatialReference": {
        "latestWkid": 4326,
        "wkid": 4326
      },
      "rings": [
        [
          [
            -122.36292,
            47.68323
          ],
          [
            -122.36303,
            47.68317
          ],
          [
            -122.36315,
            47.68315
          ],
          [
            -122.36327,
            47.68318
          ],
          [
            -122.36339,
            47.68327
          ],
          [
            -122.36345,
            47.68337
          ],
          [
            -122.36348,
            47.68349
          ],
          [
            -122.36345,
            47.68361
          ],
          [
            -122.36339,
            47.68371
          ],
          [
            -122.36325,
            47.6838
          ],
          [
            -122.36313,
            47.68383
          ],
          [
            -122.36301,
            47.6838
          ],
          [
            -122.36287,
            47.68371
          ],
          [
            -122.3628,
            47.68361
          ],
          [
            -122.36278,
            47.68347
          ],
          [
            -122.36282,
            47.68333
          ]
        ]
      ],
      "hasZ": false,
      "hasM": false
    },
    "city": "North Seattle",
    "state": "WA"
  }
]
