[
  {
    "id": 1939093,
    "startTime": 1764352763000,
    "lastUpdatedTime": 1764352923000,
    "etrTime": 1764374504000,
    "title": "Outage",
    "numPeople": 1,
    "cause": "Investigating",
    "identifier": "207607",
    "latitude": 47.61864,
    "longitude": -122.31525,
    "polygons": {
      "type": "polygon",
      "spatialReference": {
        "latestWkid": 4326,
        "wkid": 4326
      },
      "rings": [
        [
          [
            -122.31503,
            47.61838
          ],
          [
            -122.31514,
            47.61832
          ],
          [
            -122.31527,
            47.61831
          ],
          [
            -122.31538,
            47.61834
          ],
          [
            -122.3155,
            47.61842
          ],
          [
            -122.31557,
            47.61852
          ],
          [
            -122.3156,
            47.61864
          ],
          [
            -122.31557,
            47.61876
          ],
          [
            -122.3155,
            47.61887
          ],
          [
            -122.31537,
            47.61896
          ],
          [
            -122.31525,
            47.61898
          ],
          [
            -122.31513,
            47.61896
          ],
          [
            -122.31499,
            47.61887
          ],
          [
            -122.31492,
            47.61876
          ],
          [
            -122.3149,
            47.61862
          ],
          [
            -122.31494,
            47.61849
          ]
        ]
      ],
      "hasZ": false,
      "hasM": false
    },
    "city": "North Seattle",
    "state": "WA"
  },
  {
    "id": 1939101,
    "startTime": 1764353522000,
    "lastUpdatedTime": 1764353642000,
    "title": "Outage",
    "numPeople": 1,
    "cause": "Investigating",
    "identifier": "207608",
    "latitude": 47.62175,
    "longitude": -122.29645,
    "polygons": {
      "type": "polygon",
      "spatialReference": {
        "latestWkid": 4326,
        "wkid": 4326
      },
      "rings": [
        [
          [
            -122.29629,
            47.6215
          ],
          [
            -122.2964,
            47.62144
          ],
          [
            -122.29652,
            47.62143
          ],
          [
            -122.29664,
            47.62146
          ],
          [
            -122.29676,
            47.62154
          ],
          [
            -122.29683,
            47.62165
          ],
          [
            -122.29685,
            47.62177
          ],
          [
            -122.29683,
            47.62189
          ],
          [
            -122.29676,
            47.62199
          ],
          [
            -122.29662,
            47.62208
          ],
          [
            -122.2965,
            47.6221
          ],
          [
            -122.29638,
            47.62208
          ],
          [
            -122.29624,
            47.62199
          ],
          [
            -122.29617,
            47.62189
          ],
          [
            -122.29615,
            47.62174
          ],
          [
            -122.29619,
            47.62161
          ]
        ]
      ],
      "hasZ": false,
      "hasM": false
    },
    "city": "North Seattle",
    "state": "WA"
  }
]
