[
  {
    "id": 1941850,
    "startTime": 1764985610000,
    "lastUpdatedTime": 1765001419000,
    "title": "Outage",
    "numPeople": 948,
    "status": "Dispatched",
    "cause": "Investigating",
    "identifier": "207989",
    "latitude": 47.48575,
    "longitude": -122.25486,
    "polygons": {
      "type": "polygon",
      "spatialReference": {
        "latestWkid": 4326,
        "wkid": 4326
      },
      "rings": [
        [
          [
            -122.25439,
            47.47976
          ],
          [
            -122.2545,
            47.4797
          ],
          [
            -122.25462,
            47.47968
          ],
          [
            -122.25474,
            47.47971
          ],
          [
            -122.25486,
            47.4798
          ],
          [
            -122.25493,
            47.4799
          ],
          [
            -122.25495,
            47.48002
          ],
          [
            -122.25493,
            47.48014
          ],
          [
            -122.25486,
            47.48024
          ],
          [
            -122.25472,
            47.48034
          ],
          [
            -122.2546,
            47.48036
          ],
          [
            -122.25448,
            47.48034
          ],
          [
            -122.25434,
            47.48024
          ],
          [
            -122.25427,
            47.48014
          ],
          [
            -122.25425,
            47.48
          ],
          [
            -122.25429,
            47.47986
          ]
        ],
        [
          [
            -122.25581,
            47.48173
          ],
          [
            -122.25592,
            47.48167
          ],
          [
            -122.25604,
            47.48166
          ],
          [
            -122.25616,
            47.48169
          ],
          [
            -122.25628,
            47.48177
          ],
          [
            -122.25635,
            47.48187
          ],
          [
            -122.25637,
            47.48199
          ],
          [
            -122.25635,
            47.48211
          ],
          [
            -122.25628,
            47.48222
          ],
          [
            -122.25614,
            47.48231
          ],
          [
            -122.25602,
            47.48233
          ],
          [
            -122.2559,
            47.48231
          ],
          [
            -122.25576,
            47.48222
          ],
          [
            -122.25569,
            47.48211
          ],
          [
            -122.25567,
            47.48197
          ],
          [
            -122.25571,
            47.48184
          ]
        ],
        [
          [
            -122.24843,
            47.48091
          ],
          [
            -122.24854,
            47.48085
          ],
          [
            -122.24866,
            47.48083
          ],
          [
            -122.24878,
            47.48086
          ],
          [
            -122.2489,
            47.48095
          ],
          [
            -122.24897,
            47.48105
          ],
          [
            -122.24899,
            47.48117
          ],
          [
            -122.24897,
            47.48129
          ],
          [
            -122.2489,
            47.48139
          ],
          [
            -122.24876,
            47.48148
          ],
          [
            -122.24864,
            47.48151
          ],
          [
            -122.24852,
            47.48148
          ],
          [
            -122.24838,
            47.48139
          ],
          [
            -122.24832,
            47.48129
          ],
          [
            -122.24829,
            47.48115
          ],
          [
            -122.24833,
            47.48101
          ]
        ],
        [
          [
            -122.2491,
            47.47657
          ],
          [
            -122.24921,
            47.4765
          ],
          [
            -122.24933,
            47.47649
          ],
          [
            -122.24945,
            47.47652
          ],
          [
            -122.24957,
            47.4766
          ],
          [
            -122.24963,
            47.47671
          ],
          [
            -122.24966,
            47.47683
          ],
          [
            -122.24963,
            47.47695
          ],
          [
            -122.24957,
            47.47705
          ],
          [
            -122.24943,
            47.47714
          ],
          [
            -122.24931,
            47.47717
          ],
          [
            -122.24919,
            47.47714
          ],
          [
            -122.24905,
            47.47705
          ],
          [
            -122.24898,
            47.47695
          ],
          [
            -122.24896,
            47.47681
          ],
          [
            -122.249,
            47.47667
          ]
        ],
        [
          [
            -122.25358,
            47.48171
          ],
          [
            -122.25369,
            47.48165
          ],
          [
            -122.25381,
            47.48164
          ],
          [
            -122.25393,
            47.48167
          ],
          [
            -122.25405,
            47.48175
          ],
          [
            -122.25412,
            47.48185
          ],
          [
            -122.25414,
            47.48197
          ],
          [
            -122.25412,
            47.48209
          ],
          [
            -122.25405,
            47.4822
          ],
          [
            -122.25391,
            47.48229
          ],
          [
            -122.25379,
            47.48231
          ],
          [
            -122.25367,
            47.48229
          ],
          [
            -122.25353,
            47.4822
          ],
          [
            -122.25346,
            47.48209
          ],
          [
            -122.25344,
            47.48195
          ],
          [
            -122.25348,
            47.48182
          ]
        ],
        [
          [
            -122.25816,
            47.48177
          ],
          [
            -122.25827,
            47.4817
          ],
          [
            -122.25839,
            47.48169
          ],
          [
            -122.25851,
            47.48172
          ],
          [
            -122.25863,
            47.4818
          ],
          [
            -122.2587,
            47.48191
          ],
          [
            -122.25872,
            47.48203
          ],
          [
            -122.2587,
            47.48215
          ],
          [
            -122.25863,
            47.48225
          ],
          [
            -122.25849,
            47.48234
          ],
          [
            -122.25837,
            47.48236
          ],
          [
            -122.25825,
            47.48234
          ],
          [
            -122.25811,
            47.48225
          ],
          [
            -122.25805,
            47.48215
          ],
          [
            -122.25802,
            47.48201
          ],
          [
            -122.25806,
            47.48187
          ]
        ],
        [
          [
            -122.24375,
            47.48191
          ],
          [
            -122.24386,
            47.48185
          ],
          [
            -122.24398,
            47.48183
          ],
          [
            -122.2441,
            47.48186
          ],
          [
            -122.24422,
            47.48195
          ],
          [
            -122.24429,
            47.48205
          ],
          [
            -122.24431,
            47.48217
          ],
          [
            -122.24429,
            47.48229
          ],
          [
            -122.24422,
            47.48239
          ],
          [
            -122.24408,
            47.48249
          ],
          [
            -122.24396,
            47.48251
          ],
          [
            -122.24384,
            47.48249
          ],
          [
            -122.2437,
            47.48239
          ],
          [
            -122.24363,
            47.48229
          ],
          [
            -122.24361,
            47.48215
          ],
          [
            -122.24365,
            47.48201
          ]
        ],
        [
          [
            -122.25771,
            47.48643
          ],
          [
            -122.25782,
            47.48636
          ],
          [
            -122.25794,
            47.48635
          ],
          [
            -122.25806,
            47.48638
          ],
          [
            -122.25818,
            47.48646
          ],
          [
            -122.25825,
            47.48657
          ],
          [
            -122.25827,
            47.48669
          ],
          [
            -122.25825,
            47.48681
          ],
          [
            -122.25818,
            47.48691
          ],
          [
            -122.25804,
            47.487
          ],
          [
            -122.25792,
            47.48703
          ],
          [
            -122.2578,
            47.487
          ],
          [
            -122.25766,
            47.48691
          ],
          [
            -122.2576,
            47.48681
          ],
          [
            -122.25757,
            47.48667
          ],
          [
            -122.25761,
            47.48653
          ]
        ],
        [
          [
            -122.25356,
            47.4795
          ],
          [
            -122.25367,
            47.47944
          ],
          [
            -122.2538,
            47.47942
          ],
          [
            -122.25391,
            47.47945
          ],
          [
            -122.25403,
            47.47954
          ],
          [
            -122.2541,
            47.47964
          ],
          [
            -122.25413,
            47.47976
          ],
          [
            -122.2541,
            47.47988
          ],
          [
            -122.25403,
            47.47998
          ],
          [
            -122.2539,
            47.48007
          ],
          [
            -122.25378,
            47.4801
          ],
          [
            -122.25366,
            47.48007
          ],
          [
            -122.25352,
            47.47998
          ],
          [
            -122.25345,
            47.47988
          ],
          [
            -122.25343,
            47.47974
          ],
          [
            -122.25347,
            47.4796
          ]
        ],
        [
          [
            -122.25501,
            47.48419
          ],
          [
            -122.25513,
            47.48424
          ],
          [
            -122.2572,
            47.48548
          ],
          [
            -122.25721,
            47.48548
          ],
          [
            -122.25721,
            47.48549
          ],
          [
            -122.25722,
            47.4855
          ],
          [
            -122.25726,
            47.48554
          ],
          [
            -122.25729,
            47.48557
          ],
          [
            -122.2573,
            47.48558
          ],
          [
            -122.25731,
            47.48559
          ],
          [
            -122.25732,
            47.48564
          ],
          [
            -122.25734,
            47.48569
          ],
          [
            -122.25734,
            47.48569
          ],
          [
            -122.25734,
            47.48571
          ],
          [
            -122.25734,
            47.48583
          ],
          [
            -122.25733,
            47.48585
          ],
          [
            -122.25732,
            47.48587
          ],
          [
            -122.25731,
            47.48588
          ],
          [
            -122.25728,
            47.48594
          ],
          [
            -122.25724,
            47.48597
          ],
          [
            -122.25721,
            47.48601
          ],
          [
            -122.25658,
            47.48632
          ],
          [
            -122.25613,
            47.4865
          ],
          [
            -122.25601,
            47.48658
          ],
          [
            -122.25589,
            47.4866
          ],
          [
            -122.25577,
            47.48658
          ],
          [
            -122.25564,
            47.48648
          ],
          [
            -122.25557,
            47.48638
          ],
          [
            -122.25554,
            47.48624
          ],
          [
            -122.25559,
            47.48611
          ],
          [
            -122.25568,
            47.486
          ],
          [
            -122.25579,
            47.48594
          ],
          [
            -122.25585,
            47.48593
          ],
          [
            -122.2561,
            47.48581
          ],
          [
            -122.25505,
            47.48551
          ],
          [
            -122.25508,
            47.48556
          ],
          [
            -122.25505,
            47.48604
          ],
          [
            -122.25499,
            47.48619
          ],
          [
            -122.25485,
            47.48629
          ],
          [
            -122.25452,
            47.48642
          ],
          [
            -122.25495,
            47.48659
          ],
          [
            -122.25503,
            47.48669
          ],
          [
            -122.25507,
            47.4868
          ],
          [
            -122.25506,
            47.48693
          ],
          [
            -122.25501,
            47.48704
          ],
          [
            -122.25488,
            47.48713
          ],
          [
            -122.25485,
            47.48714
          ],
          [
            -122.25494,
            47.48722
          ],
          [
            -122.25502,
            47.48733
          ],
          [
            -122.25505,
            47.48745
          ],
          [
            -122.25502,
            47.48757
          ],
          [
            -122.25496,
            47.48768
          ],
          [
            -122.25485,
            47.48774
          ],
          [
            -122.25473,
            47.48777
          ],
          [
            -122.25406,
            47.4876
          ],
          [
            -122.2539,
            47.48747
          ],
          [
            -122.2537,
            47.48717
          ],
          [
            -122.25367,
            47.48699
          ],
          [
            -122.25371,
            47.48674
          ],
          [
            -122.25373,
            47.48671
          ],
          [
            -122.25371,
            47.48669
          ],
          [
            -122.25374,
            47.48649
          ],
          [
            -122.25388,
            47.48635
          ],
          [
            -122.25386,
            47.48633
          ],
          [
            -122.25386,
            47.4863
          ],
          [
            -122.25369,
            47.48648
          ],
          [
            -122.25353,
            47.48653
          ],
          [
            -122.25339,
            47.48651
          ],
          [
            -122.25328,
            47.48643
          ],
          [
            -122.25321,
            47.4863
          ],
          [
            -122.25307,
            47.4857
          ],
          [
            -122.2531,
            47.48556
          ],
          [
            -122.25321,
            47.48544
          ],
          [
            -122.25338,
            47.48539
          ],
          [
            -122.25355,
            47.4854
          ],
          [
            -122.25328,
            47.4849
          ],
          [
            -122.25325,
            47.48478
          ],
          [
            -122.25327,
            47.48464
          ],
          [
            -122.25334,
            47.48454
          ],
          [
            -122.25344,
            47.48447
          ],
          [
            -122.25356,
            47.48444
          ],
          [
            -122.25368,
            47.48447
          ],
          [
            -122.25394,
            47.48459
          ],
          [
            -122.25487,
            47.48421
          ]
        ],
        [
          [
            -122.25235,
            47.47928
          ],
          [
            -122.25246,
            47.47922
          ],
          [
            -122.25258,
            47.47921
          ],
          [
            -122.2527,
            47.47924
          ],
          [
            -122.25282,
            47.47932
          ],
          [
            -122.25289,
            47.47943
          ],
          [
            -122.25291,
            47.47955
          ],
          [
            -122.25289,
            47.47967
          ],
          [
            -122.25282,
            47.47977
          ],
          [
            -122.25268,
            47.47986
          ],
          [
            -122.25256,
            47.47988
          ],
          [
            -122.25244,
            47.47986
          ],
          [
            -122.25231,
            47.47977
          ],
          [
            -122.25224,
            47.47967
          ],
          [
            -122.25221,
            47.47953
          ],
          [
            -122.25226,
            47.47939
          ]
        ],
        [
          [
            -122.24819,
            47.48361
          ],
          [
            -122.2483,
            47.48355
          ],
          [
            -122.24842,
            47.48353
          ],
          [
            -122.24854,
            47.48356
          ],
          [
            -122.24866,
            47.48365
          ],
          [
            -122.24873,
            47.48375
          ],
          [
            -122.24875,
            47.48387
          ],
          [
            -122.24873,
            47.48399
          ],
          [
            -122.24866,
            47.48409
          ],
          [
            -122.24852,
            47.48418
          ],
          [
            -122.2484,
            47.48421
          ],
          [
            -122.24828,
            47.48418
          ],
          [
            -122.24815,
            47.48409
          ],
          [
            -122.24808,
            47.48399
          ],
          [
            -122.24805,
            47.48385
          ],
          [
            -122.2481,
            47.48371
          ]
        ],
        [
          [
            -122.24486,
            47.48102
          ],
          [
            -122.24497,
            47.48096
          ],
          [
            -122.24509,
            47.48095
          ],
          [
            -122.24521,
            47.48098
          ],
          [
            -122.24533,
            47.48106
          ],
          [
            -122.24539,
            47.48116
          ],
          [
            -122.24542,
            47.48128
          ],
          [
            -122.24539,
            47.4814
          ],
          [
            -122.24533,
            47.48151
          ],
          [
            -122.24519,
            47.4816
          ],
          [
            -122.24507,
            47.48162
          ],
          [
            -122.24495,
            47.4816
          ],
          [
            -122.24481,
            47.48151
          ],
          [
            -122.24474,
            47.4814
          ],
          [
            -122.24472,
            47.48126
          ],
          [
            -122.24476,
            47.48113
          ]
        ],
        [
          [
            -122.24478,
            47.48336
          ],
          [
            -122.24489,
            47.4833
          ],
          [
            -122.24501,
            47.48329
          ],
          [
            -122.24513,
            47.48332
          ],
          [
            -122.24525,
            47.4834
          ],
          [
            -122.24532,
            47.48351
          ],
          [
            -122.24534,
            47.48363
          ],
          [
            -122.24532,
            47.48375
          ],
          [
            -122.24525,
            47.48385
          ],
          [
            -122.24511,
            47.48394
          ],
          [
            -122.24499,
            47.48396
          ],
          [
            -122.24487,
            47.48394
          ],
          [
            -122.24473,
            47.48385
          ],
          [
            -122.24467,
            47.48375
          ],
          [
            -122.24464,
            47.4836
          ],
          [
            -122.24468,
            47.48347
          ]
        ],
        [
          [
            -122.25113,
            47.47673
          ],
          [
            -122.25124,
            47.47666
          ],
          [
            -122.25137,
            47.47665
          ],
          [
            -122.25149,
            47.47668
          ],
          [
            -122.2516,
            47.47676
          ],
          [
            -122.25167,
            47.47687
          ],
          [
            -122.2517,
            47.47699
          ],
          [
            -122.25167,
            47.47711
          ],
          [
            -122.2516,
            47.47721
          ],
          [
            -122.25147,
            47.4773
          ],
          [
            -122.25135,
            47.47732
          ],
          [
            -122.25123,
            47.4773
          ],
          [
            -122.25109,
            47.47721
          ],
          [
            -122.25102,
            47.47711
          ],
          [
            -122.251,
            47.47697
          ],
          [
            -122.25104,
            47.47683
          ]
        ],
        [
          [
            -122.25004,
            47.48192
          ],
          [
            -122.25016,
            47.48195
          ],
          [
            -122.25028,
            47.48204
          ],
          [
            -122.25035,
            47.48214
          ],
          [
            -122.25037,
            47.48226
          ],
          [
            -122.25036,
            47.4823
          ],
          [
            -122.25077,
            47.48357
          ],
          [
            -122.25077,
            47.48371
          ],
          [
            -122.2507,
            47.48384
          ],
          [
            -122.25052,
            47.48402
          ],
          [
            -122.25037,
            47.48407
          ],
          [
            -122.25019,
            47.48403
          ],
          [
            -122.25006,
            47.48388
          ],
          [
            -122.24975,
            47.48246
          ],
          [
            -122.2497,
            47.48238
          ],
          [
            -122.24967,
            47.48224
          ],
          [
            -122.24971,
            47.4821
          ],
          [
            -122.24981,
            47.482
          ],
          [
            -122.24992,
            47.48194
          ]
        ]
      ],
      "hasZ": false,
      "hasM": false
    },
    "city": "South Seattle",
    "state": "WA"
  },
  {
    "id": 1941878,
    "startTime": 1765002127000,
    "lastUpdatedTime": 1765003099000,
    "etrTime": 1765039043000,
    "title": "Outage",
    "numPeople": 94,
    "status": "Dispatched",
    "cause": "Investigating",
    "identifier": "208016",
    "latitude": 47.72898,
    "longitude": -122.29412,
    "polygons": {
      "type": "polygon",
      "spatialReference": {
        "latestWkid": 4326,
        "wkid": 4326
      },
      "rings": [
        [
          [
            -122.2939,
            47.72872
          ],
          [
            -122.29401,
            47.72866
          ],
          [
            -122.29414,
            47.72864
          ],
          [
            -122.29425,
            47.72867
          ],
          [
            -122.29437,
            47.72876
          ],
          [
            -122.29444,
            47.72886
          ],
          [
            -122.29447,
            47.72898
          ],
          [
            -122.29444,
            47.7291
          ],
          [
            -122.29437,
            47.7292
          ],
          [
            -122.29424,
            47.72929
          ],
          [
            -122.29411,
            47.72932
          ],
          [
            -122.29399,
            47.72929
          ],
          [
            -122.29386,
            47.7292
          ],
          [
            -122.29379,
            47.7291
          ],
          [
            -122.29377,
            47.72896
          ],
          [
            -122.29381,
            47.72882
          ]
        ]
      ],
      "hasZ": false,
      "hasM": false
    },
    "city": "North Seattle",
    "state": "WA"
  },
  {
    "id": 1941872,
    "startTime": 1764986400000,
    "lastUpdatedTime": 1764998651000,
    "etrTime": 1765034543000,
    "title": "Outage",
    "numPeople": 72,
    "cause": "Investigating",
    "identifier": "208010",
    "latitude": 47.48483,
    "longitude": -122.22975,
    "polygons": {
      "type": "polygon",
      "spatialReference": {
        "latestWkid": 4326,
        "wkid": 4326
      },
      "rings": [
        [
          [
            -122.2302,
            47.48344
          ],
          [
            -122.23037,
            47.48346
          ],
          [
            -122.23051,
            47.48358
          ],
          [
            -122.23056,
            47.48373
          ],
          [
            -122.23054,
            47.48444
          ],
          [
            -122.2305,
            47.48458
          ],
          [
            -122.2305,
            47.48459
          ],
          [
            -122.23059,
            47.48474
          ],
          [
            -122.2306,
            47.48499
          ],
          [
            -122.2306,
            47.485
          ],
          [
            -122.2306,
            47.48501
          ],
          [
            -122.23063,
            47.48546
          ],
          [
            -122.23067,
            47.48556
          ],
          [
            -122.23067,
            47.48568
          ],
          [
            -122.23062,
            47.4858
          ],
          [
            -122.2306,
            47.48582
          ],
          [
            -122.2306,
            47.4859
          ],
          [
            -122.23048,
            47.48607
          ],
          [
            -122.23031,
            47.48614
          ],
          [
            -122.22999,
            47.48612
          ],
          [
            -122.22997,
            47.48611
          ],
          [
            -122.22984,
            47.48612
          ],
          [
            -122.2297,
            47.48608
          ],
          [
            -122.22907,
            47.48566
          ],
          [
            -122.22875,
            47.48537
          ],
          [
            -122.22862,
            47.48502
          ],
          [
            -122.22863,
            47.48488
          ],
          [
            -122.22865,
            47.48484
          ],
          [
            -122.22865,
            47.48483
          ],
          [
            -122.22866,
            47.48471
          ],
          [
            -122.22871,
            47.4846
          ],
          [
            -122.22882,
            47.48451
          ],
          [
            -122.22896,
            47.48448
          ],
          [
            -122.22915,
            47.48448
          ],
          [
            -122.22911,
            47.48446
          ],
          [
            -122.22887,
            47.48429
          ],
          [
            -122.22879,
            47.4842
          ],
          [
            -122.22875,
            47.48408
          ],
          [
            -122.22876,
            47.48396
          ],
          [
            -122.22881,
            47.48385
          ],
          [
            -122.22891,
            47.48377
          ],
          [
            -122.22904,
            47.48373
          ],
          [
            -122.22918,
            47.48375
          ],
          [
            -122.22946,
            47.48389
          ],
          [
            -122.22955,
            47.48394
          ],
          [
            -122.22955,
            47.4839
          ],
          [
            -122.22961,
            47.48375
          ],
          [
            -122.22972,
            47.48366
          ]
        ]
      ],
      "hasZ": false,
      "hasM": false
    },
    "city": "South Seattle",
    "state": "WA"
  },
  {
    "id": 1941841,
    "startTime": 1764987416000,
    "lastUpdatedTime": 1764988685000,
    "etrTime": 1765010243000,
    "title": "Outage",
    "numPeople": 70,
    "cause": "Investigating",
    "identifier": "207983",
    "latitude": 47.55676,
    "longitude": -122.29698,
    "polygons": {
      "type": "polygon",
      "spatialReference": {
        "latestWkid": 4326,
        "wkid": 4326
      },
      "rings": [
        [
          [
            -122.29741,
            47.55346
          ],
          [
            -122.29773,
            47.55355
          ],
          [
            -122.29786,
            47.55364
          ],
          [
            -122.29793,
            47.55378
          ],
          [
            -122.29792,
            47.55394
          ],
          [
            -122.29784,
            47.55407
          ],
          [
            -122.29752,
            47.55438
          ],
          [
            -122.29754,
            47.55442
          ],
          [
            -122.29756,
            47.55456
          ],
          [
            -122.29751,
            47.55509
          ],
          [
            -122.29745,
            47.5552
          ],
          [
            -122.29736,
            47.55528
          ],
          [
            -122.29733,
            47.55529
          ],
          [
            -122.29744,
            47.55532
          ],
          [
            -122.29752,
            47.55541
          ],
          [
            -122.29757,
            47.55554
          ],
          [
            -122.29755,
            47.5558
          ],
          [
            -122.29751,
            47.55592
          ],
          [
            -122.29747,
            47.55595
          ],
          [
            -122.29748,
            47.55594
          ],
          [
            -122.29763,
            47.55594
          ],
          [
            -122.29776,
            47.556
          ],
          [
            -122.29802,
            47.55628
          ],
          [
            -122.29807,
            47.55639
          ],
          [
            -122.29809,
            47.55664
          ],
          [
            -122.29807,
            47.55679
          ],
          [
            -122.29831,
            47.55679
          ],
          [
            -122.29845,
            47.55683
          ],
          [
            -122.29854,
            47.55691
          ],
          [
            -122.2986,
            47.55704
          ],
          [
            -122.2986,
            47.55718
          ],
          [
            -122.29841,
            47.55761
          ],
          [
            -122.29832,
            47.55772
          ],
          [
            -122.29815,
            47.55778
          ],
          [
            -122.29746,
            47.55775
          ],
          [
            -122.29743,
            47.55775
          ],
          [
            -122.2974,
            47.55795
          ],
          [
            -122.29746,
            47.55819
          ],
          [
            -122.2974,
            47.55838
          ],
          [
            -122.29732,
            47.55847
          ],
          [
            -122.29697,
            47.55869
          ],
          [
            -122.29727,
            47.55873
          ],
          [
            -122.2974,
            47.55878
          ],
          [
            -122.29749,
            47.55886
          ],
          [
            -122.29754,
            47.55898
          ],
          [
            -122.29753,
            47.55936
          ],
          [
            -122.29751,
            47.5594
          ],
          [
            -122.29752,
            47.55954
          ],
          [
            -122.29747,
            47.55975
          ],
          [
            -122.29731,
            47.55987
          ],
          [
            -122.29667,
            47.56009
          ],
          [
            -122.29655,
            47.5601
          ],
          [
            -122.29643,
            47.56006
          ],
          [
            -122.29634,
            47.55998
          ],
          [
            -122.29629,
            47.55987
          ],
          [
            -122.29628,
            47.55975
          ],
          [
            -122.29633,
            47.55961
          ],
          [
            -122.29635,
            47.55959
          ],
          [
            -122.29582,
            47.55942
          ],
          [
            -122.29572,
            47.55931
          ],
          [
            -122.29568,
            47.55916
          ],
          [
            -122.29583,
            47.55871
          ],
          [
            -122.29596,
            47.5586
          ],
          [
            -122.29612,
            47.55857
          ],
          [
            -122.29621,
            47.55858
          ],
          [
            -122.29622,
            47.55797
          ],
          [
            -122.29624,
            47.55793
          ],
          [
            -122.29609,
            47.55779
          ],
          [
            -122.29602,
            47.5576
          ],
          [
            -122.29607,
            47.55742
          ],
          [
            -122.2963,
            47.55717
          ],
          [
            -122.29638,
            47.55711
          ],
          [
            -122.2963,
            47.55706
          ],
          [
            -122.29622,
            47.55691
          ],
          [
            -122.29621,
            47.55656
          ],
          [
            -122.29624,
            47.55644
          ],
          [
            -122.29624,
            47.55644
          ],
          [
            -122.29622,
            47.55598
          ],
          [
            -122.29623,
            47.55594
          ],
          [
            -122.2962,
            47.55589
          ],
          [
            -122.29625,
            47.5555
          ],
          [
            -122.29636,
            47.55534
          ],
          [
            -122.29647,
            47.5553
          ],
          [
            -122.2961,
            47.55507
          ],
          [
            -122.29601,
            47.55497
          ],
          [
            -122.29597,
            47.55483
          ],
          [
            -122.296,
            47.55467
          ],
          [
            -122.29617,
            47.55448
          ],
          [
            -122.29614,
            47.55442
          ],
          [
            -122.29615,
            47.55412
          ],
          [
            -122.29628,
            47.55378
          ],
          [
            -122.29636,
            47.55366
          ],
          [
            -122.29651,
            47.55359
          ]
        ]
      ],
      "hasZ": false,
      "hasM": false
    },
    "city": "South Seattle",
    "state": "WA"
  },
  {
    "id": 1941837,
    "startTime": 1764986517000,
    "lastUpdatedTime": 1764991925000,
    "etrTime": 1765008443000,
    "title": "Outage",
    "numPeople": 63,
    "cause": "Investigating",
    "identifier": "207976",
    "latitude": 47.54894,
    "longitude": -122.38643,
    "polygons": {
      "type": "polygon",
      "spatialReference": {
        "latestWkid": 4326,
        "wkid": 4326
      },
      "rings": [
        [
          [
            -122.38641,
            47.54942
          ],
          [
            -122.38592,
            47.54935
          ],
          [
            -122.38576,
            47.54922
          ],
          [
            -122.3857,
            47.54909
          ],
          [
            -122.38568,
            47.54876
          ],
          [
            -122.38572,
            47.54863
          ],
          [
            -122.38582,
            47.54852
          ],
          [
            -122.38597,
            47.54847
          ],
          [
            -122.3868,
            47.54846
          ],
          [
            -122.38693,
            47.5485
          ],
          [
            -122.38704,
            47.5486
          ],
          [
            -122.38721,
            47.54898
          ],
          [
            -122.38721,
            47.54918
          ],
          [
            -122.38715,
            47.54931
          ],
          [
            -122.38705,
            47.54939
          ],
          [
            -122.38694,
            47.54943
          ]
        ]
      ],
      "hasZ": false,
      "hasM": false
    },
    "city": "South Seattle",
    "state": "WA"
  },
  {
    "id": 1941880,
    "startTime": 1764986400000,
    "lastUpdatedTime": 1765004051000,
    "etrTime": 1765025543000,
    "title": "Outage",
    "numPeople": 25,
    "cause": "Investigating",
    "identifier": "208019",
    "latitude": 47.55283,
    "longitude": -122.37559,
    "polygons": {
      "type": "polygon",
      "spatialReference": {
        "latestWkid": 4326,
        "wkid": 4326
      },
      "rings": [
        [
          [
            -122.37521,
            47.55178
          ],
          [
            -122.37602,
            47.5519
          ],
          [
            -122.37613,
            47.55196
          ],
          [
            -122.37621,
            47.55205
          ],
          [
            -122.37628,
            47.55236
          ],
          [
            -122.37619,
            47.55291
          ],
          [
            -122.37623,
            47.55301
          ],
          [
            -122.37623,
            47.55348
          ],
          [
            -122.37619,
            47.55362
          ],
          [
            -122.37611,
            47.55371
          ],
          [
            -122.37599,
            47.55377
          ],
          [
            -122.37543,
            47.5539
          ],
          [
            -122.37523,
            47.55386
          ],
          [
            -122.37513,
            47.55377
          ],
          [
            -122.37492,
            47.55344
          ],
          [
            -122.37496,
            47.55289
          ],
          [
            -122.37502,
            47.55264
          ],
          [
            -122.37494,
            47.55213
          ],
          [
            -122.37495,
            47.55201
          ],
          [
            -122.37504,
            47.55186
          ]
        ]
      ],
      "hasZ": false,
      "hasM": false
    },
    "city": "South Seattle",
    "state": "WA"
  },
  {
    "id": 1941871,
    "startTime": 1764985505000,
    "lastUpdatedTime": 1764997451000,
    "title": "Outage",
    "numPeople": 8,
    "cause": "Investigating",
    "identifier": "208008",
    "latitude": 47.48375,
    "longitude": -122.22119,
    "polygons": {
      "type": "polygon",
      "spatialReference": {
        "latestWkid": 4326,
        "wkid": 4326
      },
      "rings": [
        [
          [
            -122.2195,
            47.4823
          ],
          [
            -122.21961,
            47.48224
          ],
          [
            -122.21973,
            47.48222
          ],
          [
            -122.21985,
            47.48226
          ],
          [
            -122.21997,
            47.48234
          ],
          [
            -122.22004,
            47.48244
          ],
          [
            -122.22006,
            47.48256
          ],
          [
            -122.22004,
            47.48268
          ],
          [
            -122.21997,
            47.48279
          ],
          [
            -122.21983,
            47.48288
          ],
          [
            -122.21971,
            47.4829
          ],
          [
            -122.21959,
            47.48288
          ],
          [
            -122.21945,
            47.48279
          ],
          [
            -122.21938,
            47.48268
          ],
          [
            -122.21936,
            47.48254
          ],
          [
            -122.2194,
            47.48241
          ]
        ],
        [
          [
            -122.22198,
            47.4832
          ],
          [
            -122.22212,
            47.48322
          ],
          [
            -122.22224,
            47.48329
          ],
          [
            -122.22231,
            47.4834
          ],
          [
            -122.22233,
            47.48352
          ],
          [
            -122.22231,
            47.48364
          ],
          [
            -122.22224,
            47.48374
          ],
          [
            -122.2221,
            47.48382
          ],
          [
            -122.22157,
            47.48394
          ],
          [
            -122.2212,
            47.48399
          ],
          [
            -122.22107,
            47.48395
          ],
          [
            -122.22101,
            47.48407
          ],
          [
            -122.22091,
            47.48416
          ],
          [
            -122.22066,
            47.48428
          ],
          [
            -122.22041,
            47.48435
          ],
          [
            -122.22029,
            47.48435
          ],
          [
            -122.22013,
            47.48427
          ],
          [
            -122.22004,
            47.48408
          ],
          [
            -122.22007,
            47.4839
          ],
          [
            -122.22021,
            47.48376
          ],
          [
            -122.22046,
            47.48364
          ],
          [
            -122.2207,
            47.48357
          ],
          [
            -122.22083,
            47.48357
          ],
          [
            -122.2209,
            47.4836
          ],
          [
            -122.22094,
            47.48351
          ],
          [
            -122.22112,
            47.48338
          ]
        ]
      ],
      "hasZ": false,
      "hasM": false
    },
    "city": "South Seattle",
    "state": "WA"
  },
  {
    "id": 1941881,
    "type": "PLANNED_OUTAGE",
    "startTime": 1765004030000,
    "lastUpdatedTime": 1765004172000,
    "title": "Planned Outage",
    "numPeople": 8,
    "status": "Dispatched",
    "cause": "Planned Outage",
    "identifier": "208020",
    "latitude": 47.6203,
    "longitude": -122.33325,
    "polygons": {
      "type": "polygon",
      "spatialReference": {
        "latestWkid": 4326,
        "wkid": 4326
      },
      "rings": [
        [
          [
            -122.33265,
            47.62019
          ],
          [
            -122.33375,
            47.61981
          ],
          [
            -122.33388,
            47.61983
          ],
          [
            -122.33398,
            47.61989
          ],
          [
            -122.33406,
            47.61999
          ],
          [
            -122.33409,
            47.6201
          ],
          [
            -122.33405,
            47.62028
          ],
          [
            -122.33391,
            47.62041
          ],
          [
            -122.33335,
            47.62062
          ],
          [
            -122.33278,
            47.6208
          ],
          [
            -122.33257,
            47.62073
          ],
          [
            -122.33245,
            47.62054
          ],
          [
            -122.33249,
            47.62033
          ]
        ]
      ],
      "hasZ": false,
      "hasM": false
    },
    "city": "North Seattle",
    "state": "WA"
  },
  {
    "id": 1941851,
    "startTime": 1764989343000,
    "lastUpdatedTime": 1764994924000,
    "etrTime": 1765011143000,
    "title": "Outage",
    "numPeople": 2,
    "status": "Dispatched",
    "cause": "Equipment Failure",
    "identifier": "207991",
    "latitude": 47.66664,
    "longitude": -122.27671,
    "polygons": {
      "type": "polygon",
      "spatialReference": {
        "latestWkid": 4326,
        "wkid": 4326
      },
      "rings": [
        [
          [
            -122.27633,
            47.66626
          ],
          [
            -122.27675,
            47.6663
          ],
          [
            -122.27724,
            47.66642
          ],
          [
            -122.27733,
            47.66651
          ],
          [
            -122.27738,
            47.66662
          ],
          [
            -122.27739,
            47.66674
          ],
          [
            -122.27735,
            47.66685
          ],
          [
            -122.27724,
            47.66697
          ],
          [
            -122.27708,
            47.66701
          ],
          [
            -122.27663,
            47.66697
          ],
          [
            -122.27614,
            47.66684
          ],
          [
            -122.27601,
            47.66669
          ],
          [
            -122.276,
            47.66647
          ],
          [
            -122.27613,
            47.66631
          ]
        ]
      ],
      "hasZ": false,
      "hasM": false
    },
    "city": "North Seattle",
    "state": "WA"
  },
  {
    "id": 1941648,
    "type": "PLANNED_OUTAGE",
    "startTime": 1764965415000,
    "lastUpdatedTime": 1764965764000,
    "etrTime": 1766693640000,
    "title": "Planned Outage",
    "numPeople": 1,
    "status": "Dispatched",
    "cause": "Planned Outage",
    "identifier": "207929",
    "latitude": 47.69917,
    "longitude": -122.34116,
    "polygons": {
      "type": "polygon",
      "spatialReference": {
        "latestWkid": 4326,
        "wkid": 4326
      },
      "rings": [
        [
          [
            -122.34094,
            47.69891
          ],
          [
            -122.34105,
            47.69885
          ],
          [
            -122.34117,
            47.69883
          ],
          [
            -122.34129,
            47.69887
          ],
          [
            -122.34141,
            47.69895
          ],
          [
            -122.34148,
            47.69905
          ],
          [
            -122.3415,
            47.69917
          ],
          [
            -122.34148,
            47.69929
          ],
          [
            -122.34141,
            47.69939
          ],
          [
            -122.34127,
            47.69949
          ],
          [
            -122.34115,
            47.69951
          ],
          [
            -122.34103,
            47.69949
          ],
          [
            -122.34089,
            47.69939
          ],
          [
            -122.34083,
            47.69929
          ],
          [
            -122.3408,
            47.69915
          ],
          [
            -122.34084,
            47.69902
          ]
        ]
      ],
      "hasZ": false,
      "hasM": false
    },
    "city": "North Seattle",
    "state": "WA"
  },
  {
    "id": 1941768,
    "type": "PLANNED_OUTAGE",
    "startTime": 1764971189000,
    "lastUpdatedTime": 1764971409000,
    "etrTime": 1766699280000,
    "title": "Planned Outage",
    "numPeople": 1,
    "status": "Dispatched",
    "cause": "Planned Outage",
    "identifier": "207936",
    "latitude": 47.48833,
    "longitude": -122.32016,
    "polygons": {
      "type": "polygon",
      "spatialReference": {
        "latestWkid": 4326,
        "wkid": 4326
      },
      "rings": [
        [
          [
            -122.31994,
            47.48807
          ],
          [
            -122.32005,
            47.48801
          ],
          [
            -122.32018,
            47.48799
          ],
          [
            -122.32029,
            47.48802
          ],
          [
            -122.32041,
            47.48811
          ],
          [
            -122.32048,
            47.48821
          ],
          [
            -122.3205,
            47.48833
          ],
          [
            -122.32048,
            47.48845
          ],
          [
            -122.32041,
            47.48855
          ],
          [
            -122.32027,
            47.48864
          ],
          [
            -122.32015,
            47.48867
          ],
          [
            -122.32003,
            47.48864
          ],
          [
            -122.3199,
            47.48855
          ],
          [
            -122.31983,
            47.48845
          ],
          [
            -122.3198,
            47.48831
          ],
          [
            -122.31985,
            47.48817
          ]
        ]
      ],
      "hasZ": false,
      "hasM": false
    },
    "city": "South Seattle",
    "state": "WA"
  },
  {
    "id": 1941798,
    "type": "PLANNED_OUTAGE",
    "startTime": 1764975288000,
    "lastUpdatedTime": 1764975369000,
    "etrTime": 1766703300000,
    "title": "Planned Outage",
    "numPeople": 1,
    "status": "Dispatched",
    "cause": "Planned Outage",
    "identifier": "207943",
    "latitude": 47.64412,
    "longitude": -122.349,
    "polygons": {
      "type": "polygon",
      "spatialReference": {
        "latestWkid": 4326,
        "wkid": 4326
      },
      "rings": [
        [
          [
            -122.34884,
            47.64388
          ],
          [
            -122.34895,
            47.64382
          ],
          [
            -122.34907,
            47.6438
          ],
          [
            -122.34919,
            47.64383
          ],
          [
            -122.34931,
            47.64392
          ],
          [
            -122.34938,
            47.64402
          ],
          [
            -122.3494,
            47.64414
          ],
          [
            -122.34938,
            47.64426
          ],
          [
            -122.34931,
            47.64436
          ],
          [
            -122.34917,
            47.64445
          ],
          [
            -122.34905,
            47.64448
          ],
          [
            -122.34893,
            47.64445
          ],
          [
            -122.34879,
            47.64436
          ],
          [
            -122.34872,
            47.64426
          ],
          [
            -122.3487,
            47.64412
          ],
          [
            -122.34874,
            47.64398
          ]
        ]
      ],
      "hasZ": false,
      "hasM": false
    },
    "city": "North Seattle",
    "state": "WA"
  },
  {
    "id": 1941807,
    "startTime": 1764977599000,
    "lastUpdatedTime": 1765003699000,
    "etrTime": 1765015200000,
    "title": "Outage",
    "numPeople": 1,
    "status": "Dispatched",
    "cause": "Investigating",
    "identifier": "207946",
    "latitude": 47.50317,
    "longitude": -122.36485,
    "polygons": {
      "type": "polygon",
      "spatialReference": {
        "latestWkid": 4326,
        "wkid": 4326
      },
      "rings": [
        [
          [
            -122.36453,
            47.50287
          ],
          [
            -122.36464,
            47.50281
          ],
          [
            -122.36476,
            47.50279
          ],
          [
            -122.36488,
            47.50282
          ],
          [
            -122.365,
            47.50291
          ],
          [
            -122.36507,
            47.50301
          ],
          [
            -122.36509,
            47.50313
          ],
          [
            -122.36507,
            47.50325
          ],
          [
            -122.365,
            47.50335
          ],
          [
            -122.36486,
            47.50344
          ],
          [
            -122.36474,
            47.50347
          ],
          [
            -122.36462,
            47.50344
          ],
          [
            -122.36449,
            47.50335
          ],
          [
            -122.36442,
            47.50325
          ],
          [
            -122.36439,
            47.50311
          ],
          [
            -122.36444,
            47.50297
          ]
        ]
      ],
      "hasZ": false,
      "hasM": false
    },
    "city": "South Seattle",
    "state": "WA"
  },
  {
    "id": 1941845,
    "startTime": 1764988408000,
    "lastUpdatedTime": 1764990725000,
    "etrTime": 1765024643000,
    "title": "Outage",
    "numPeople": 1,
    "status": "Dispatched",
    "cause": "Investigating",
    "identifier": "207986",
    "latitude": 47.56278,
    "longitude": -122.358,
    "polygons": {
      "type": "polygon",
      "spatialReference": {
        "latestWkid": 4326,
        "wkid": 4326
      },
      "rings": [
        [
          [
            -122.35768,
            47.56248
          ],
          [
            -122.35779,
            47.56242
          ],
          [
            -122.35791,
            47.5624
          ],
          [
            -122.35803,
            47.56243
          ],
          [
            -122.35815,
            47.56252
          ],
          [
            -122.35822,
            47.56262
          ],
          [
            -122.35824,
            47.56274
          ],
          [
            -122.35822,
            47.56286
          ],
          [
            -122.35815,
            47.56296
          ],
          [
            -122.35801,
            47.56305
          ],
          [
            -122.35789,
            47.56308
          ],
          [
            -122.35777,
            47.56305
          ],
          [
            -122.35763,
            47.56296
          ],
          [
            -122.35757,
            47.56286
          ],
          [
            -122.35754,
            47.56272
          ],
          [
            -122.35758,
            47.56258
          ]
        ]
      ],
      "hasZ": false,
      "hasM": false
    },
    "city": "South Seattle",
    "state": "WA"
  }
]
