[
  {
    "id": 1883577,
    "startTime": 1753021671000,
    "lastUpdatedTime": 1753068364000,
    "etrTime": 1753079400000,
    "title": "Outage",
    "numPeople": 56,
    "cause": "Investigating",
    "identifier": "199816",
    "latitude": 47.6033,
    "longitude": -122.29287,
    "polygons": {
      "type": "polygon",
      "spatialReference": {
        "latestWkid": 4326,
        "wkid": 4326
      },
      "rings": [
        [
          [
            -122.29355,
            47.60115
          ],
          [
            -122.29373,
            47.60125
          ],
          [
            -122.29381,
            47.60144
          ],
          [
            -122.29379,
            47.60156
          ],
          [
            -122.29362,
            47.60203
          ],
          [
            -122.29325,
            47.60251
          ],
          [
            -122.29349,
            47.60284
          ],
          [
            -122.29352,
            47.60298
          ],
          [
            -122.29349,
            47.60312
          ],
          [
            -122.2934,
            47.60321
          ],
          [
            -122.29343,
            47.60324
          ],
          [
            -122.29345,
            47.60338
          ],
          [
            -122.29326,
            47.60403
          ],
          [
            -122.29317,
            47.60421
          ],
          [
            -122.29318,
            47.60423
          ],
          [
            -122.29329,
            47.60475
          ],
          [
            -122.29327,
            47.60497
          ],
          [
            -122.29312,
            47.60525
          ],
          [
            -122.29302,
            47.60531
          ],
          [
            -122.29289,
            47.60534
          ],
          [
            -122.29241,
            47.60533
          ],
          [
            -122.29228,
            47.60528
          ],
          [
            -122.29216,
            47.60517
          ],
          [
            -122.29202,
            47.60487
          ],
          [
            -122.292,
            47.60468
          ],
          [
            -122.29214,
            47.60422
          ],
          [
            -122.29216,
            47.60419
          ],
          [
            -122.2921,
            47.6041
          ],
          [
            -122.29206,
            47.60363
          ],
          [
            -122.29208,
            47.60331
          ],
          [
            -122.29214,
            47.60318
          ],
          [
            -122.29223,
            47.6031
          ],
          [
            -122.29237,
            47.60306
          ],
          [
            -122.2925,
            47.60306
          ],
          [
            -122.29248,
            47.60301
          ],
          [
            -122.29257,
            47.60239
          ],
          [
            -122.29253,
            47.60235
          ],
          [
            -122.29247,
            47.60211
          ],
          [
            -122.29246,
            47.60178
          ],
          [
            -122.29252,
            47.60165
          ],
          [
            -122.29291,
            47.6012
          ],
          [
            -122.29305,
            47.60116
          ]
        ]
      ],
      "hasZ": false,
      "hasM": false
    },
    "city": "South Seattle",
    "state": "WA"
  },
  {
    "id": 1883530,
    "startTime": 1753052825000,
    "lastUpdatedTime": 1753067644000,
    "etrTime": 1753103560000,
    "title": "Outage",
    "numPeople": 27,
    "status": "Dispatched",
    "cause": "Investigating",
    "identifier": "199812",
    "latitude": 47.61939,
    "longitude": -122.32132,
    "polygons": {
      "type": "polygon",
      "spatialReference": {
        "latestWkid": 4326,
        "wkid": 4326
      },
      "rings": [
        [
          [
            -122.32099,
            47.61971
          ],
          [
            -122.32102,
            47.61926
          ],
          [
            -122.32115,
            47.6189
          ],
          [
            -122.32124,
            47.61882
          ],
          [
            -122.32135,
            47.61877
          ],
          [
            -122.32147,
            47.61877
          ],
          [
            -122.32159,
            47.61882
          ],
          [
            -122.32168,
            47.61892
          ],
          [
            -122.32173,
            47.61908
          ],
          [
            -122.32162,
            47.61978
          ],
          [
            -122.32157,
            47.6199
          ],
          [
            -122.32141,
            47.62002
          ],
          [
            -122.32121,
            47.62002
          ],
          [
            -122.32105,
            47.6199
          ]
        ]
      ],
      "hasZ": false,
      "hasM": false
    },
    "city": "North Seattle",
    "state": "WA"
  },
  {
    "id": 1883493,
    "startTime": 1753045405000,
    "lastUpdatedTime": 1753067644000,
    "etrTime": 1753089160000,
    "title": "Outage",
    "numPeople": 14,
    "status": "Dispatched",
    "cause": "Investigating",
    "identifier": "199806",
    "latitude": 47.65056,
    "longitude": -122.36688,
    "polygons": {
      "type": "polygon",
      "spatialReference": {
        "latestWkid": 4326,
        "wkid": 4326
      },
      "rings": [
        [
          [
            -122.36701,
            47.65104
          ],
          [
            -122.36657,
            47.65099
          ],
          [
            -122.36622,
            47.65083
          ],
          [
            -122.36614,
            47.65074
          ],
          [
            -122.3661,
            47.65063
          ],
          [
            -122.3661,
            47.6505
          ],
          [
            -122.36616,
            47.65039
          ],
          [
            -122.36631,
            47.65029
          ],
          [
            -122.36713,
            47.65004
          ],
          [
            -122.36728,
            47.65003
          ],
          [
            -122.36741,
            47.65009
          ],
          [
            -122.36752,
            47.65026
          ],
          [
            -122.36751,
            47.65046
          ],
          [
            -122.36727,
            47.65093
          ],
          [
            -122.36716,
            47.65102
          ]
        ]
      ],
      "hasZ": false,
      "hasM": false
    },
    "city": "North Seattle",
    "state": "WA"
  },
  {
    "id": 1883570,
    "startTime": 1753067785000,
    "lastUpdatedTime": 1753068364000,
    "etrTime": 1753068364000,
    "title": "Outage",
    "numPeople": 1,
    "cause": "Investigating",
    "identifier": "199815",
    "latitude": 47.46662,
    "longitude": -122.34291,
    "polygons": {
      "type": "polygon",
      "spatialReference": {
        "latestWkid": 4326,
        "wkid": 4326
      },
      "rings": [
        [
          [
            -122.34264,
            47.46634
          ],
          [
            -122.34276,
            47.46627
          ],
          [
            -122.34288,
            47.46626
          ],
          [
            -122.343,
            47.46629
          ],
          [
            -122.34311,
            47.46637
          ],
          [
            -122.34318,
            47.46648
          ],
          [
            -122.34321,
            47.4666
          ],
          [
            -122.34318,
            47.46672
          ],
          [
            -122.34311,
            47.46682
          ],
          [
            -122.34298,
            47.46691
          ],
          [
            -122.34286,
            47.46693
          ],
          [
            -122.34274,
            47.46691
          ],
          [
            -122.3426,
            47.46682
          ],
          [
            -122.34253,
            47.46672
          ],
          [
            -122.34251,
            47.46658
          ],
          [
            -122.34255,
            47.46644
          ]
        ]
      ],
      "hasZ": false,
      "hasM": false
    },
    "city": "South Seattle",
    "state": "WA"
  }
]
